{
  "events": [
    {
      "idEvent": "1300001",
      "idLeague": "4391",
      "strLeague": "NFL",
      "strSport": "American Football",
      "strEvent": "Kansas City Chiefs vs Buffalo Bills",
      "strHomeTeam": "Kansas City Chiefs",
      "strAwayTeam": "Buffalo Bills",
      "idHomeTeam": "134918",
      "idAwayTeam": "134919",
      "intHomeScore": null,
      "intAwayScore": null,
      "dateEvent": "2026-06-23",
      "strTime": "20:20:00",
      "strTimestamp": "2026-06-23T20:20:00",
      "strRound": "Week 1",
      "strVenue": "Arrowhead Stadium",
      "strTVStation": "NBC",
      "strStatus": "Not Started",
      "strProgress": ""
    }
  ]
}
